{"rowCount":6,"colCount":6,"type":0,"letters":"تحقل","words":[{"word":"تحلق","vertical":false,"rowIndex":2,"colIndex":2,"coinIndices":[],"awardCoins":false},{"word":"حلت","vertical":true,"rowIndex":3,"colIndex":1,"coinIndices":[],"awardCoins":false},{"word":"قتل","vertical":true,"rowIndex":1,"colIndex":2,"coinIndices":[],"awardCoins":false},{"word":"قلت","vertical":true,"rowIndex":2,"colIndex":5,"coinIndices":[],"awardCoins":false},{"word":"تحل","vertical":false,"rowIndex":3,"colIndex":0,"coinIndices":[],"awardCoins":false},{"word":"حقل","vertical":true,"rowIndex":0,"colIndex":4,"coinIndices":[],"awardCoins":false},{"word":"تلحق","vertical":false,"rowIndex":5,"colIndex":1,"coinIndices":[],"awardCoins":false},{"word":"لحق","vertical":false,"rowIndex":0,"colIndex":3,"coinIndices":[],"awardCoins":false},{"word":"تحق","vertical":false,"rowIndex":1,"colIndex":0,"coinIndices":[],"awardCoins":false}],"id":"a368b9b4d2e4f23b52a3a5601057f94b"}