{"rowCount":4,"colCount":5,"type":0,"letters":"رقلني","words":[{"word":"ري","vertical":false,"rowIndex":0,"colIndex":1,"coinIndices":[],"awardCoins":false},{"word":"نقل","vertical":false,"rowIndex":3,"colIndex":0,"coinIndices":[],"awardCoins":false},{"word":"قلي","vertical":true,"rowIndex":0,"colIndex":4,"coinIndices":[],"awardCoins":false},{"word":"ينقل","vertical":true,"rowIndex":0,"colIndex":2,"coinIndices":[],"awardCoins":false},{"word":"نيل","vertical":false,"rowIndex":1,"colIndex":2,"coinIndices":[],"awardCoins":false}],"id":"b0d889cd968f5203d84c88c327af594c"}